aitools/__init__.py
aitools/aitools.py
aitools/cli.py
aitools-1.0.0.dist-info/AUTHORS.rst
aitools-1.0.0.dist-info/LICENSE
aitools-1.0.0.dist-info/METADATA
aitools-1.0.0.dist-info/WHEEL
aitools-1.0.0.dist-info/entry_points.txt
aitools-1.0.0.dist-info/top_level.txt
aitools-1.0.0.dist-info/RECORD
