Metadata-Version: 2.1
Name: aitools
Version: 1.0.0
Summary: Artificial Intelligence Tools Kit
Home-page: https://github.com/imohitawasthi/aitools
Author: Mohit Awasthi
Author-email: imohitawasthi@gmail.com
License: Apache Software License 2.0
Keywords: aitools
Platform: UNKNOWN
Classifier: Development Status :: 2 - Pre-Alpha
Classifier: Intended Audience :: Developers
Classifier: License :: OSI Approved :: Apache Software License
Classifier: Natural Language :: English
Classifier: Programming Language :: Python :: 3
Classifier: Programming Language :: Python :: 3.6
Classifier: Programming Language :: Python :: 3.7
Classifier: Programming Language :: Python :: 3.8
Requires-Python: >=3.6
Requires-Dist: Click (>=7.0)
